scadnano/__init__.py
scadnano/modifications.py
scadnano/origami_rectangle.py
scadnano/scadnano.py
scadnano_test-0.17.1.dist-info/LICENSE.txt
scadnano_test-0.17.1.dist-info/METADATA
scadnano_test-0.17.1.dist-info/WHEEL
scadnano_test-0.17.1.dist-info/top_level.txt
scadnano_test-0.17.1.dist-info/RECORD
