Metadata-Version: 2.1
Name: scadnano-test
Version: 0.17.1
Summary: Python scripting library for generating designs readable by scadnano.
Home-page: https://github.com/UC-Davis-molecular-computing/scadnano-python-package
Author: David Doty
Author-email: doty@ucdavis.edu
License: MIT
Download-URL: https://github.com/UC-Davis-molecular-computing/scadnano-python-package/archive/v0.17.0.zip
Platform: UNKNOWN
Requires-Python: >=3.6
License-File: LICENSE.txt
Requires-Dist: xlwt
Requires-Dist: dataclasses (>=0.6) ; python_version < "3.7"
